pixhawk_lib/__init__.py
pixhawk_lib/decorators.py
pixhawk_lib/pixhawk.py
pixhawk_lib/tunes.py
pixhawk_lib/tests/__init__.py
pixhawk_lib/tests/flask_runner.py
pixhawk_lib/tests/test_land.py
pixhawk_lib/tests/test_pixhawk.py
pixhawk_lib-0.2.4.dist-info/licenses/LICENSE
pixhawk_lib-0.2.4.dist-info/METADATA
pixhawk_lib-0.2.4.dist-info/WHEEL
pixhawk_lib-0.2.4.dist-info/top_level.txt
pixhawk_lib-0.2.4.dist-info/RECORD
