Metadata-Version: 2.4
Name: pixhawk-lib
Version: 0.2.4
Summary: A simple library for controlling Pixhawk drones easy.
Author-email: Sharikian <wacoinseig@gmail.com>
License: MIT License
Project-URL: Homepage, https://github.com/sharikian/pixhawk-lib
Project-URL: Repository, https://github.com/sharikian/pixhawk-lib
Requires-Python: >=3.9
License-File: LICENSE
Requires-Dist: dronekit>=2.9.2
Requires-Dist: pymavlink>=2.4.40
Requires-Dist: pyserial
Requires-Dist: flask
Dynamic: license-file
